remoteev3/__init__.py
remoteev3/client.py
remoteev3/server.py
remoteev3-0.1.0.dist-info/METADATA
remoteev3-0.1.0.dist-info/WHEEL
remoteev3-0.1.0.dist-info/top_level.txt
remoteev3-0.1.0.dist-info/RECORD
