Metadata-Version: 2.1
Name: remoteev3
Version: 0.1.0
Summary: Remote API for ev3dev
Author: Maciej Stryjewski
Author-email: stryjewski.mac@gmail.com
Requires-Dist: rpyc ==6.0.2
